easy_rouge-0.2.2.dist-info/METADATA
easy_rouge-0.2.2.dist-info/RECORD
easy_rouge-0.2.2.dist-info/WHEEL
easy_rouge-0.2.2.dist-info/top_level.txt
rouge/__init__.py
rouge/rouge.py
rouge/tests/__init__.py
rouge/tests/test_rouge_l.py
rouge/tests/test_rouge_n.py
rouge/tests/test_rouge_score.py
rouge/tests/test_rouge_w.py
rouge/tests/wrapper.py
rouge/tests/data/ROUGE-test.json
