Metadata-Version: 2.1
Name: easy-rouge
Version: 0.2.2
Summary: An implementation of ROUGE family metrics for automatic summarization
Home-page: https://github.com/neural-dialogue-metrics/rouge.git
Author: cgsdfc
Author-email: cgsdfc@126.com
License: LICENCE.txt
Keywords: NL,CL,MT,natural language processing,computational linguistics,automatic summarization
Platform: UNKNOWN
Classifier: Intended Audience :: Science/Research
Classifier: Programming Language :: Python :: 3
Classifier: License :: OSI Approved :: MIT License
Classifier: Topic :: Text Processing :: Linguistic
Classifier: Operating System :: OS Independent
